{
  "name": "Toro Movers — Lead Funnels Drip (labor + full-service)",
  "nodes": [
    {
      "parameters": {
        "httpMethod": "POST",
        "path": "toro-funnel-lead",
        "responseMode": "lastNode",
        "options": {}
      },
      "id": "webhook",
      "name": "Webhook",
      "type": "n8n-nodes-base.webhook",
      "typeVersion": 2,
      "position": [
        -820,
        360
      ],
      "webhookId": "toro-funnel-lead",
      "notes": "Set N8N_FUNNEL_WEBHOOK_URL on Netlify to this node's Production URL. Both /labor-only-moving and /full-service-moving post here; the IF routes by funnel."
    },
    {
      "parameters": {
        "conditions": {
          "options": {
            "caseSensitive": true,
            "version": 2
          },
          "combinator": "and",
          "conditions": [
            {
              "leftValue": "={{ $json.body.funnel }}",
              "rightValue": "labor",
              "operator": {
                "type": "string",
                "operation": "equals"
              }
            }
          ]
        },
        "options": {}
      },
      "id": "is-labor",
      "name": "Funnel = labor?",
      "type": "n8n-nodes-base.if",
      "typeVersion": 2,
      "position": [
        -580,
        360
      ]
    },
    {
      "parameters": {
        "amount": 2,
        "unit": "days"
      },
      "id": "l-wait2",
      "name": "Labor wait 2d",
      "type": "n8n-nodes-base.wait",
      "typeVersion": 1.1,
      "position": [
        -80,
        140
      ],
      "webhookId": "l-wait2"
    },
    {
      "parameters": {
        "method": "POST",
        "url": "https://api.resend.com/emails",
        "sendHeaders": true,
        "headerParameters": {
          "parameters": [
            {
              "name": "Authorization",
              "value": "=Bearer {{$env.RESEND_API_KEY}}"
            }
          ]
        },
        "sendBody": true,
        "specifyBody": "json",
        "jsonBody": "={\n  \"from\": \"Toro Movers <hello@toromovers.net>\",\n  \"to\": [\"{{ $('Webhook').item.json.body.email }}\"],\n  \"subject\": \"Still need a crew? We're quick on labor-only\",\n  \"html\": \"<p>Hi {{ $('Webhook').item.json.body.firstName }} — you keep the truck, we bring the muscle. Loading, unloading, stairs by the hour, priced up front. <a href='https://toromovers.net/quote'>Check availability</a>.</p>\"\n}",
        "options": {}
      },
      "id": "l-email2",
      "name": "Labor Email 2 (day 2)",
      "type": "n8n-nodes-base.httpRequest",
      "typeVersion": 4.2,
      "position": [
        140,
        140
      ]
    },
    {
      "parameters": {
        "amount": 3,
        "unit": "days"
      },
      "id": "l-wait3",
      "name": "Labor wait 3d",
      "type": "n8n-nodes-base.wait",
      "typeVersion": 1.1,
      "position": [
        360,
        140
      ],
      "webhookId": "l-wait3"
    },
    {
      "parameters": {
        "method": "POST",
        "url": "https://api.resend.com/emails",
        "sendHeaders": true,
        "headerParameters": {
          "parameters": [
            {
              "name": "Authorization",
              "value": "=Bearer {{$env.RESEND_API_KEY}}"
            }
          ]
        },
        "sendBody": true,
        "specifyBody": "json",
        "jsonBody": "={\n  \"from\": \"Toro Movers <hello@toromovers.net>\",\n  \"to\": [\"{{ $('Webhook').item.json.body.email }}\"],\n  \"subject\": \"Ready to book your labor help?\",\n  \"html\": \"<p>Hi {{ $('Webhook').item.json.body.firstName }} — family-owned, insured, 4.9 on Google. We'll lock in a crew with up-front hourly pricing. <a href='https://toromovers.net/quote'>Get my hourly quote</a> or call (689) 600-2720.</p>\"\n}",
        "options": {}
      },
      "id": "l-email3",
      "name": "Labor Email 3 (day 5)",
      "type": "n8n-nodes-base.httpRequest",
      "typeVersion": 4.2,
      "position": [
        580,
        140
      ]
    },
    {
      "parameters": {
        "conditions": {
          "options": {
            "caseSensitive": true,
            "version": 2
          },
          "combinator": "and",
          "conditions": [
            {
              "leftValue": "={{ $('Webhook').item.json.body.smsConsent }}",
              "rightValue": true,
              "operator": {
                "type": "boolean",
                "operation": "true",
                "singleValue": true
              }
            }
          ]
        },
        "options": {}
      },
      "id": "l-sms-gate",
      "name": "Labor SMS consent?",
      "type": "n8n-nodes-base.if",
      "typeVersion": 2,
      "position": [
        -300,
        360
      ]
    },
    {
      "parameters": {
        "amount": 3,
        "unit": "days"
      },
      "id": "l-wait-s2",
      "name": "Labor sms wait 3d",
      "type": "n8n-nodes-base.wait",
      "typeVersion": 1.1,
      "position": [
        140,
        360
      ],
      "webhookId": "l-wait-s2"
    },
    {
      "parameters": {
        "method": "POST",
        "url": "https://api.openphone.com/v1/messages",
        "sendHeaders": true,
        "headerParameters": {
          "parameters": [
            {
              "name": "Authorization",
              "value": "={{$env.OPENPHONE_API_KEY}}"
            }
          ]
        },
        "sendBody": true,
        "specifyBody": "json",
        "jsonBody": "={\n  \"from\": \"{{$env.OPENPHONE_FROM_NUMBER}}\",\n  \"to\": [\"{{ $('Webhook').item.json.body.phone }}\"],\n  \"content\": \"Still need movers for the day? We can check availability fast and price by the hour: https://toromovers.net/quote — Toro Movers. STOP to opt out.\"\n}",
        "options": {}
      },
      "id": "l-sms2",
      "name": "Labor SMS 2 (day 3)",
      "type": "n8n-nodes-base.httpRequest",
      "typeVersion": 4.2,
      "position": [
        360,
        360
      ]
    },
    {
      "parameters": {
        "amount": 2,
        "unit": "days"
      },
      "id": "f-wait2",
      "name": "Full wait 2d",
      "type": "n8n-nodes-base.wait",
      "typeVersion": 1.1,
      "position": [
        -80,
        620
      ],
      "webhookId": "f-wait2"
    },
    {
      "parameters": {
        "method": "POST",
        "url": "https://api.resend.com/emails",
        "sendHeaders": true,
        "headerParameters": {
          "parameters": [
            {
              "name": "Authorization",
              "value": "=Bearer {{$env.RESEND_API_KEY}}"
            }
          ]
        },
        "sendBody": true,
        "specifyBody": "json",
        "jsonBody": "={\n  \"from\": \"Toro Movers <hello@toromovers.net>\",\n  \"to\": [\"{{ $('Webhook').item.json.body.email }}\"],\n  \"subject\": \"We'll handle the whole move — carefully\",\n  \"html\": \"<p>Hi {{ $('Webhook').item.json.body.firstName }} — full-service means you don't lift a box. We pack, protect, load, transport, and set everything up. Want packing too? Just say the word. <a href='https://toromovers.net/quote'>Get my quote</a>.</p>\"\n}",
        "options": {}
      },
      "id": "f-email2",
      "name": "Full Email 2 (day 2)",
      "type": "n8n-nodes-base.httpRequest",
      "typeVersion": 4.2,
      "position": [
        140,
        620
      ]
    },
    {
      "parameters": {
        "amount": 3,
        "unit": "days"
      },
      "id": "f-wait3",
      "name": "Full wait 3d",
      "type": "n8n-nodes-base.wait",
      "typeVersion": 1.1,
      "position": [
        360,
        620
      ],
      "webhookId": "f-wait3"
    },
    {
      "parameters": {
        "method": "POST",
        "url": "https://api.resend.com/emails",
        "sendHeaders": true,
        "headerParameters": {
          "parameters": [
            {
              "name": "Authorization",
              "value": "=Bearer {{$env.RESEND_API_KEY}}"
            }
          ]
        },
        "sendBody": true,
        "specifyBody": "json",
        "jsonBody": "={\n  \"from\": \"Toro Movers <hello@toromovers.net>\",\n  \"to\": [\"{{ $('Webhook').item.json.body.email }}\"],\n  \"subject\": \"Ready for a stress-free move?\",\n  \"html\": \"<p>Hi {{ $('Webhook').item.json.body.firstName }} — family-owned, insured, 4.9 on Google. 'On time, professional, handled everything with care.' When you're ready we'll lock in your full-service date. <a href='https://toromovers.net/quote'>Request full-service pricing</a> or call (689) 600-2720.</p>\"\n}",
        "options": {}
      },
      "id": "f-email3",
      "name": "Full Email 3 (day 5)",
      "type": "n8n-nodes-base.httpRequest",
      "typeVersion": 4.2,
      "position": [
        580,
        620
      ]
    },
    {
      "parameters": {
        "conditions": {
          "options": {
            "caseSensitive": true,
            "version": 2
          },
          "combinator": "and",
          "conditions": [
            {
              "leftValue": "={{ $('Webhook').item.json.body.smsConsent }}",
              "rightValue": true,
              "operator": {
                "type": "boolean",
                "operation": "true",
                "singleValue": true
              }
            }
          ]
        },
        "options": {}
      },
      "id": "f-sms-gate",
      "name": "Full SMS consent?",
      "type": "n8n-nodes-base.if",
      "typeVersion": 2,
      "position": [
        -300,
        840
      ]
    },
    {
      "parameters": {
        "amount": 3,
        "unit": "days"
      },
      "id": "f-wait-s2",
      "name": "Full sms wait 3d",
      "type": "n8n-nodes-base.wait",
      "typeVersion": 1.1,
      "position": [
        140,
        840
      ],
      "webhookId": "f-wait-s2"
    },
    {
      "parameters": {
        "method": "POST",
        "url": "https://api.openphone.com/v1/messages",
        "sendHeaders": true,
        "headerParameters": {
          "parameters": [
            {
              "name": "Authorization",
              "value": "={{$env.OPENPHONE_API_KEY}}"
            }
          ]
        },
        "sendBody": true,
        "specifyBody": "json",
        "jsonBody": "={\n  \"from\": \"{{$env.OPENPHONE_FROM_NUMBER}}\",\n  \"to\": [\"{{ $('Webhook').item.json.body.phone }}\"],\n  \"content\": \"Want us to handle the whole move? Family-owned, insured, up-front pricing. Get your full-service quote: https://toromovers.net/quote — Toro Movers. STOP to opt out.\"\n}",
        "options": {}
      },
      "id": "f-sms2",
      "name": "Full SMS 2 (day 3)",
      "type": "n8n-nodes-base.httpRequest",
      "typeVersion": 4.2,
      "position": [
        360,
        840
      ]
    }
  ],
  "connections": {
    "Webhook": {
      "main": [
        [
          {
            "node": "Funnel = labor?",
            "type": "main",
            "index": 0
          }
        ]
      ]
    },
    "Funnel = labor?": {
      "main": [
        [
          {
            "node": "Labor wait 2d",
            "type": "main",
            "index": 0
          },
          {
            "node": "Labor SMS consent?",
            "type": "main",
            "index": 0
          }
        ],
        [
          {
            "node": "Full wait 2d",
            "type": "main",
            "index": 0
          },
          {
            "node": "Full SMS consent?",
            "type": "main",
            "index": 0
          }
        ]
      ]
    },
    "Labor wait 2d": {
      "main": [
        [
          {
            "node": "Labor Email 2 (day 2)",
            "type": "main",
            "index": 0
          }
        ]
      ]
    },
    "Labor Email 2 (day 2)": {
      "main": [
        [
          {
            "node": "Labor wait 3d",
            "type": "main",
            "index": 0
          }
        ]
      ]
    },
    "Labor wait 3d": {
      "main": [
        [
          {
            "node": "Labor Email 3 (day 5)",
            "type": "main",
            "index": 0
          }
        ]
      ]
    },
    "Labor SMS consent?": {
      "main": [
        [
          {
            "node": "Labor sms wait 3d",
            "type": "main",
            "index": 0
          }
        ],
        []
      ]
    },
    "Labor sms wait 3d": {
      "main": [
        [
          {
            "node": "Labor SMS 2 (day 3)",
            "type": "main",
            "index": 0
          }
        ]
      ]
    },
    "Full wait 2d": {
      "main": [
        [
          {
            "node": "Full Email 2 (day 2)",
            "type": "main",
            "index": 0
          }
        ]
      ]
    },
    "Full Email 2 (day 2)": {
      "main": [
        [
          {
            "node": "Full wait 3d",
            "type": "main",
            "index": 0
          }
        ]
      ]
    },
    "Full wait 3d": {
      "main": [
        [
          {
            "node": "Full Email 3 (day 5)",
            "type": "main",
            "index": 0
          }
        ]
      ]
    },
    "Full SMS consent?": {
      "main": [
        [
          {
            "node": "Full sms wait 3d",
            "type": "main",
            "index": 0
          }
        ],
        []
      ]
    },
    "Full sms wait 3d": {
      "main": [
        [
          {
            "node": "Full SMS 2 (day 3)",
            "type": "main",
            "index": 0
          }
        ]
      ]
    }
  },
  "settings": {
    "executionOrder": "v1"
  },
  "active": false
}
